ffxivcalc/Enemy.py
ffxivcalc/Fight.py
ffxivcalc/__init__.py
ffxivcalc/__main__.py
ffxivcalc/API/API.py
ffxivcalc/API/__init__.py
ffxivcalc/API/library.py
ffxivcalc/API/Model/ObjectInModel.py
ffxivcalc/API/Model/ObjectOutModel.py
ffxivcalc/API/Model/__init__.py
ffxivcalc/GearSolver/Gear.py
ffxivcalc/GearSolver/Solver.py
ffxivcalc/GearSolver/__init__.py
ffxivcalc/Jobs/ActionEnum.py
ffxivcalc/Jobs/Base_Spell.py
ffxivcalc/Jobs/Player.py
ffxivcalc/Jobs/PlayerEnum.py
ffxivcalc/Jobs/__init__.py
ffxivcalc/Jobs/Caster/Caster_Spell.py
ffxivcalc/Jobs/Caster/__init__.py
ffxivcalc/Jobs/Caster/Blackmage/BlackMage_Spell.py
ffxivcalc/Jobs/Caster/Blackmage/__init__.py
ffxivcalc/Jobs/Caster/Redmage/Redmage_Spell.py
ffxivcalc/Jobs/Caster/Redmage/__init__.py
ffxivcalc/Jobs/Caster/Summoner/Summoner_Spell.py
ffxivcalc/Jobs/Caster/Summoner/__init__.py
ffxivcalc/Jobs/Healer/Healer_Spell.py
ffxivcalc/Jobs/Healer/__init__.py
ffxivcalc/Jobs/Healer/Astrologian/Astrologian_Spell.py
ffxivcalc/Jobs/Healer/Astrologian/__init__.py
ffxivcalc/Jobs/Healer/Sage/Sage_Spell.py
ffxivcalc/Jobs/Healer/Sage/__init__.py
ffxivcalc/Jobs/Healer/Scholar/Scholar_Spell.py
ffxivcalc/Jobs/Healer/Scholar/__init__.py
ffxivcalc/Jobs/Healer/Whitemage/Whitemage_Spell.py
ffxivcalc/Jobs/Healer/Whitemage/__init__.py
ffxivcalc/Jobs/Melee/Melee_Spell.py
ffxivcalc/Jobs/Melee/__init__.py
ffxivcalc/Jobs/Melee/Dragoon/Dragoon_Spell.py
ffxivcalc/Jobs/Melee/Dragoon/__init__.py
ffxivcalc/Jobs/Melee/Monk/Monk_Spell.py
ffxivcalc/Jobs/Melee/Monk/__init__.py
ffxivcalc/Jobs/Melee/Ninja/Ninja_Spell.py
ffxivcalc/Jobs/Melee/Ninja/__init__.py
ffxivcalc/Jobs/Melee/Reaper/Reaper_Spell.py
ffxivcalc/Jobs/Melee/Reaper/__init__.py
ffxivcalc/Jobs/Melee/Samurai/Samurai_Spell.py
ffxivcalc/Jobs/Melee/Samurai/__init__.py
ffxivcalc/Jobs/Ranged/Ranged_Spell.py
ffxivcalc/Jobs/Ranged/__init__.py
ffxivcalc/Jobs/Ranged/Bard/Bard_Spell.py
ffxivcalc/Jobs/Ranged/Bard/__init__.py
ffxivcalc/Jobs/Ranged/Dancer/Dancer_Spell.py
ffxivcalc-0.8.940.dist-info/License.md
ffxivcalc-0.8.940.dist-info/METADATA
ffxivcalc-0.8.940.dist-info/WHEEL
ffxivcalc-0.8.940.dist-info/top_level.txt
ffxivcalc-0.8.940.dist-info/RECORD
