Metadata-Version: 2.1
Name: ffxivcalc
Version: 0.8.940
Summary: DPS simulator for Final Fantasy XIV.
Home-page: https://github.com/IAmPythagoras/FFXIV-Combat-Simulator
Author: Anthony Desrochers
Author-email: anthony.desrochers17@gmail.com
Project-URL: Source, https://github.com/IAmPythagoras/FFXIV-Combat-Simulator
Project-URL: Site, https://ffxivdpscalc.azurewebsites.net/simulate/
Project-URL: Documentation, https://iampythagoras.github.io/index.html
Keywords: ffxiv,xiv,dps,simulator,ffxiv-combat-simulator
Classifier: Development Status :: 4 - Beta
Classifier: Topic :: Software Development :: Build Tools
Classifier: License :: OSI Approved :: MIT License
Classifier: Programming Language :: Python :: 3.10
Requires-Python: >=3.10
License-File: License.md
Requires-Dist: contourpy
Requires-Dist: cycler
Requires-Dist: fonttools
Requires-Dist: kiwisolver
Requires-Dist: matplotlib
Requires-Dist: numpy
Requires-Dist: packaging
Requires-Dist: Pillow
Requires-Dist: pyparsing
Requires-Dist: python-dateutil
Requires-Dist: six
Requires-Dist: coreapi
Requires-Dist: pandas
Requires-Dist: python-graphql-client
